mergeconf/__init__.py
mergeconf/exceptions.py
mergeconf/mergeconf.py
mergeconf/mergeconfitem.py
mergeconf/mergeconfsection.py
mergeconf-0.6.0.dist-info/LICENSE
mergeconf-0.6.0.dist-info/METADATA
mergeconf-0.6.0.dist-info/WHEEL
mergeconf-0.6.0.dist-info/top_level.txt
mergeconf-0.6.0.dist-info/RECORD
