Metadata-Version: 2.1
Name: mergeconf
Version: 0.6.0
Summary: Library for reading configuration from file, environment and arguments
Home-page: https://gitlab.com/dleske/mergeconf
Author: Drew Leske
Author-email: drew@leske.net
Project-URL: Bug Tracker, https://gitlab.com/dleske/mergeconf/-/issues
Classifier: Programming Language :: Python :: 3
Classifier: License :: OSI Approved :: MIT License
Classifier: Operating System :: OS Independent
Requires-Python: >=3.6
License-File: LICENSE
